MANIFEST.in
README.rst
setup.py
pytsm/__init__.py
pytsm/core.py
pytsm/formatter.py
pytsm/texttable.py
pytsm.egg-info/PKG-INFO
pytsm.egg-info/SOURCES.txt
pytsm.egg-info/dependency_links.txt
pytsm.egg-info/entry_points.txt
pytsm.egg-info/requires.txt
pytsm.egg-info/top_level.txt
pytsm/actions/__init__.py
pytsm/actions/__main__.py
pytsm/actions/base.py
pytsm/actions/commands/__init__.py
pytsm/actions/commands/activity_history.py
pytsm/actions/commands/cmd.py
pytsm/actions/commands/daily_report.py
pytsm/actions/commands/help.py
pytsm/actions/commands/node_stg_per_filespace.py
pytsm/actions/commands/process_list.py
pytsm/actions/commands/schedule.py
pytsm/actions/commands/usage.py
pytsm/actions/commands/volume_details.py
pytsm/actions/commands/volume_list.py