Metadata-Version: 1.1
Name: pytsm
Version: 0.0.1
Summary: Small python library to monitor TSM
Home-page: https://github.com/vpac/pytsm/
Author: Brian May
Author-email: brian@v3.org.au
License: GPL3+
Keywords: tsm
Platform: UNKNOWN
Classifier: Development Status :: 5 - Production/Stable
Classifier: Intended Audience :: Developers
Classifier: License :: OSI Approved :: GNU Lesser General Public License v3 or later (LGPLv3+)
Classifier: Operating System :: OS Independent
Classifier: Programming Language :: Python :: 2
Classifier: Programming Language :: Python :: 3
Classifier: Topic :: Software Development :: Libraries :: Python Modules
